{"_type":"export","__export_format":4,"__export_date":"2020-01-31T03:53:45.234Z","__export_source":"insomnia.desktop.app:v7.0.6","resources":[{"_id":"req_63abdd7dbe11457db66022d8237117bc","authentication":{},"body":{"mimeType":"application/json","text":"{\n\t\"fullName\": \"Huberto Kaiser Filho\",\n\t\"gender\": \"male\",\n\t\"birthDate\": \"03/04/1991\",\n\t\"age\": \"28\",\n\t\"city\": \"5e33a16a12fa0c0d9b1d2baf\"\n}"},"created":1580441565772,"description":"","headers":[{"id":"pair_823b27c2e7994ffdb733e78a2ddc37af","name":"Content-Type","value":"application/json"}],"isPrivate":false,"metaSortKey":-1580441556526,"method":"POST","modified":1580442145547,"name":"Insert","parameters":[],"parentId":"fld_980ada49877949a1857f14d3bd11c031","settingDisableRenderRequestBody":false,"settingEncodeUrl":true,"settingFollowRedirects":"global","settingRebuildPath":true,"settingSendCookies":true,"settingStoreCookies":true,"url":"{{ host  }}/api/v1/client","_type":"request"},{"_id":"fld_980ada49877949a1857f14d3bd11c031","created":1580441565693,"description":"","environment":{},"environmentPropertyOrder":null,"metaSortKey":-1580441494650,"modified":1580441568452,"name":"Client","parentId":"wrk_446cd965e85140d7a6dba2dda19dc1ca","_type":"request_group"},{"_id":"wrk_446cd965e85140d7a6dba2dda19dc1ca","created":1580441479404,"description":"","modified":1580441479404,"name":"Compasso","parentId":null,"_type":"workspace"},{"_id":"req_ffdfd5b94b15411eb5c9325623898409","authentication":{},"body":{},"created":1580441565736,"description":"","headers":[],"isPrivate":false,"metaSortKey":-1580441551156,"method":"GET","modified":1580442700387,"name":"Get","parameters":[],"parentId":"fld_980ada49877949a1857f14d3bd11c031","settingDisableRenderRequestBody":false,"settingEncodeUrl":true,"settingFollowRedirects":"global","settingRebuildPath":true,"settingSendCookies":true,"settingStoreCookies":true,"url":"{{ host  }}/api/v1/client/5e33a442b32ddf14bffb02c5","_type":"request"},{"_id":"req_c6855dc381ff437089a2d89c8217580a","authentication":{},"body":{},"created":1580441565753,"description":"","headers":[],"isPrivate":false,"metaSortKey":-1580441548471,"method":"GET","modified":1580441670448,"name":"GetAll","parameters":[],"parentId":"fld_980ada49877949a1857f14d3bd11c031","settingDisableRenderRequestBody":false,"settingEncodeUrl":true,"settingFollowRedirects":"global","settingRebuildPath":true,"settingSendCookies":true,"settingStoreCookies":true,"url":"{{ host  }}/api/v1/clients","_type":"request"},{"_id":"req_774d5a3f3d854c60845a2c92d75ab3b5","authentication":{},"body":{"mimeType":"application/json","text":"{\n\t\"fullName\": \"Huberto Kaiser Filho\",\n\t\"gender\": \"male\",\n\t\"birthDate\": \"03/04/1991\",\n\t\"age\": \"28\",\n\t\"city\": \"5e33a16a12fa0c0d9b1d2baf\"\n}"},"created":1580441565764,"description":"","headers":[{"id":"pair_00973923e81c49df93d0da6424d610a1","name":"Content-Type","value":"application/json"}],"isPrivate":false,"metaSortKey":-1580441523222,"method":"PUT","modified":1580442121106,"name":"Edit","parameters":[],"parentId":"fld_980ada49877949a1857f14d3bd11c031","settingDisableRenderRequestBody":false,"settingEncodeUrl":true,"settingFollowRedirects":"global","settingRebuildPath":true,"settingSendCookies":true,"settingStoreCookies":true,"url":"{{ host  }}/api/v1/client/5e33a1e817631a0ed62931c6","_type":"request"},{"_id":"req_da81ecbf51cf4493aae2855c7a927fbc","authentication":{},"body":{},"created":1580441565770,"description":"","headers":[],"isPrivate":false,"metaSortKey":-1580441523172,"method":"DELETE","modified":1580442132043,"name":"Delete","parameters":[],"parentId":"fld_980ada49877949a1857f14d3bd11c031","settingDisableRenderRequestBody":false,"settingEncodeUrl":true,"settingFollowRedirects":"global","settingRebuildPath":true,"settingSendCookies":true,"settingStoreCookies":true,"url":"{{ host  }}/api/v1/client/5e33a1e817631a0ed62931c6","_type":"request"},{"_id":"req_9d2c87321704468d8257259c4a130859","authentication":{},"body":{"mimeType":"application/json","text":"{\n\t\"name\": \"Pelotas\",\n\t\"state\": \"Rio Grande do Sul\"\n}"},"created":1580441556526,"description":"","headers":[{"id":"pair_fb7569683e5d4e2fb9490397280674b0","name":"Content-Type","value":"application/json"}],"isPrivate":false,"metaSortKey":-1580441556526,"method":"POST","modified":1580441736214,"name":"Insert","parameters":[],"parentId":"fld_5ce177778ae8426e9b5b4641e1c26a37","settingDisableRenderRequestBody":false,"settingEncodeUrl":true,"settingFollowRedirects":"global","settingRebuildPath":true,"settingSendCookies":true,"settingStoreCookies":true,"url":"{{ host  }}/api/v1/city","_type":"request"},{"_id":"fld_5ce177778ae8426e9b5b4641e1c26a37","created":1580441494600,"description":"","environment":{},"environmentPropertyOrder":null,"metaSortKey":-1580441494600,"modified":1580441494600,"name":"City","parentId":"wrk_446cd965e85140d7a6dba2dda19dc1ca","_type":"request_group"},{"_id":"req_d53b6821e10b4c27b5f26487b645d2e6","authentication":{},"body":{},"created":1580441506339,"description":"","headers":[],"isPrivate":false,"metaSortKey":-1580441553841,"method":"GET","modified":1580441840265,"name":"Get","parameters":[],"parentId":"fld_5ce177778ae8426e9b5b4641e1c26a37","settingDisableRenderRequestBody":false,"settingEncodeUrl":true,"settingFollowRedirects":"global","settingRebuildPath":true,"settingSendCookies":true,"settingStoreCookies":true,"url":"{{ host  }}/api/v1/city/5e33a0e112fa0c0d9b1d2bae","_type":"request"},{"_id":"req_0422649996eb422981cc01d0f584ae5d","authentication":{},"body":{},"created":1580441513314,"description":"","headers":[],"isPrivate":false,"metaSortKey":-1580441551156,"method":"GET","modified":1580441923358,"name":"GetAll","parameters":[],"parentId":"fld_5ce177778ae8426e9b5b4641e1c26a37","settingDisableRenderRequestBody":false,"settingEncodeUrl":true,"settingFollowRedirects":"global","settingRebuildPath":true,"settingSendCookies":true,"settingStoreCookies":true,"url":"{{ host  }}/api/v1/cities?state=Rio de Janeiro","_type":"request"},{"_id":"req_2cfb3b7085254b8d99264b1558e4fe7b","authentication":{},"body":{"mimeType":"application/json","text":"{\n\t\"name\": \"Rio de Janeiro\",\n\t\"state\": \"Rio de Janeiro\"\n}"},"created":1580441523222,"description":"","headers":[{"id":"pair_449c9f60c0b34b598ed0a6ed14fe6f01","name":"Content-Type","value":"application/json"}],"isPrivate":false,"metaSortKey":-1580441523222,"method":"PUT","modified":1580441901683,"name":"Edit","parameters":[],"parentId":"fld_5ce177778ae8426e9b5b4641e1c26a37","settingDisableRenderRequestBody":false,"settingEncodeUrl":true,"settingFollowRedirects":"global","settingRebuildPath":true,"settingSendCookies":true,"settingStoreCookies":true,"url":"{{ host  }}/api/v1/city/5e33a0e112fa0c0d9b1d2bae","_type":"request"},{"_id":"req_4046939c136043d4920cd1735601c8d5","authentication":{},"body":{},"created":1580441545786,"description":"","headers":[],"isPrivate":false,"metaSortKey":-1580441523172,"method":"DELETE","modified":1580441935666,"name":"Delete","parameters":[],"parentId":"fld_5ce177778ae8426e9b5b4641e1c26a37","settingDisableRenderRequestBody":false,"settingEncodeUrl":true,"settingFollowRedirects":"global","settingRebuildPath":true,"settingSendCookies":true,"settingStoreCookies":true,"url":"{{ host  }}/api/v1/city/5e33a0e112fa0c0d9b1d2bae","_type":"request"},{"_id":"env_db6a5ab7c7575b56eee56a8366c811c93a0f3fe4","color":null,"created":1580441479565,"data":{"host":"http://localhost:1337"},"dataPropertyOrder":{"&":["host"]},"isPrivate":false,"metaSortKey":1580441479565,"modified":1580441617860,"name":"Base Environment","parentId":"wrk_446cd965e85140d7a6dba2dda19dc1ca","_type":"environment"},{"_id":"jar_db6a5ab7c7575b56eee56a8366c811c93a0f3fe4","cookies":[{"creation":"2020-01-31T03:35:39.267Z","domain":"localhost","hostOnly":true,"httpOnly":true,"id":"36761721225128174","key":"sails.sid","lastAccessed":"2020-01-31T03:51:30.443Z","path":"/","value":"s%3AVyks-8YQpRLPwwsHIx5VU63s4rsTZUHM.B9sP2xDaXzU%2FFujINSzg%2FxXkfq5tHnxYRCzMc4H2W1A"}],"created":1580441479567,"modified":1580442690443,"name":"Default Jar","parentId":"wrk_446cd965e85140d7a6dba2dda19dc1ca","_type":"cookie_jar"}]}